zjbs_file_client/__init__.py
zjbs_file_client/client.py
zjbs_file_client/model.py
zjbs_file_client-0.10.0.dist-info/METADATA
zjbs_file_client-0.10.0.dist-info/WHEEL
zjbs_file_client-0.10.0.dist-info/licenses/LICENSE.txt
zjbs_file_client-0.10.0.dist-info/RECORD
