Metadata-Version: 2.1
Name: zjbs-file-client
Version: 0.10.0
Summary: The file client of ZJBrainSciencePlatform
Author-email: 蔡涛 <caitao@zhejianglab.com>
License: GPL-3.0-only
License-File: LICENSE.txt
Requires-Python: >=3.11
Requires-Dist: httpx>=0.25.0
